aiorisk/__init__.py
aiorisk/base/__init__.py
aiorisk/base/api_client.py
aiorisk/base/app.py
aiorisk/clients/__init__.py
aiorisk/clients/ari_client.py
aiorisk/dispatcher/__init__.py
aiorisk/dispatcher/dispatcher.py
aiorisk/enums.py
aiorisk/errors/__init__.py
aiorisk/errors/asterisk.py
aiorisk/models/__init__.py
aiorisk/models/base_models.py
aiorisk/models/event_models.py
aiorisk/models/send_models.py
aiorisk/models_api/AsteriskAPI.py
aiorisk/models_api/BridgeAPI.py
aiorisk/models_api/ChannelAPI.py
aiorisk/models_api/DeviceStateAPI.py
aiorisk/models_api/EndpointAPI.py
aiorisk/models_api/MailboxesAPI.py
aiorisk/models_api/PlaybackControlAPI.py
aiorisk/models_api/RecordingAPI.py
aiorisk/models_api/ResourceAPI.py
aiorisk/models_api/Response.py
aiorisk/models_api/SoundAPI.py
aiorisk/models_api/StasisApplicationAPI.py
aiorisk/models_api/WebsocketResource.py
aiorisk/models_api/__init__.py
aiorisk-0.1.2.1.dist-info/LICENCE
aiorisk-0.1.2.1.dist-info/METADATA
aiorisk-0.1.2.1.dist-info/WHEEL
aiorisk-0.1.2.1.dist-info/RECORD
